scren_tools/__init__.py
scren_tools-1.1.5.dist-info/METADATA
scren_tools-1.1.5.dist-info/WHEEL
scren_tools-1.1.5.dist-info/top_level.txt
scren_tools-1.1.5.dist-info/RECORD
