Metadata-Version: 2.4
Name: scren_tools
Version: 1.1.5
Summary: Ultimate full page screenshot library
Home-page: https://github.com/username/scrt
Author: Abolfazl
Classifier: Programming Language :: Python :: 3
Classifier: Operating System :: OS Independent
Requires-Python: >=3.7
Requires-Dist: pyppeteer
Requires-Dist: requests
Dynamic: author
Dynamic: classifier
Dynamic: home-page
Dynamic: requires-dist
Dynamic: requires-python
Dynamic: summary
